mlx2md/__init__.py
mlx2md/__main__.py
mlx2md-0.1.4.dist-info/METADATA
mlx2md-0.1.4.dist-info/WHEEL
mlx2md-0.1.4.dist-info/top_level.txt
mlx2md-0.1.4.dist-info/RECORD
